MANIFEST.in
README.md
VERSION
setup.py
rpcviaredis/__init__.py
rpcviaredis/client.py
rpcviaredis/example.py
rpcviaredis/exceptions.py
rpcviaredis/models.py
rpcviaredis/server.py
rpcviaredis/transport.py
rpcviaredis.egg-info/PKG-INFO
rpcviaredis.egg-info/SOURCES.txt
rpcviaredis.egg-info/dependency_links.txt
rpcviaredis.egg-info/requires.txt
rpcviaredis.egg-info/top_level.txt