Metadata-Version: 1.1
Name: rpcviaredis
Version: 0.1.1
Summary: Build RPC pattern via redis connection
Home-page: https://github.com/moas/rpcviaredis
Author: Oscar LASM
Author-email: lasm.landry@gmail.com
License: GNU V2.0
Keywords: Redis,RPC
Platform: UNKNOWN
Classifier: Programming Language :: Python :: 3
Classifier: Programming Language :: Python :: 3.3
Classifier: Programming Language :: Python :: 3.4
Classifier: Development Status :: 2 - Pre-Alpha
Classifier: License :: OSI Approved :: GNU General Public License v2 or later (GPLv2+)
Classifier: Natural Language :: French
Classifier: Operating System :: OS Independent
Classifier: Topic :: Software Development :: Libraries :: Python Modules
Classifier: Topic :: Software Development :: Object Brokering
Classifier: Topic :: System :: Distributed Computing
